f4/Builder.py
f4/Parser.py
f4/Transformer.py
f4/Utilities.py
f4/__init__.py
f4-1.1.1.dist-info/LICENSE
f4-1.1.1.dist-info/METADATA
f4-1.1.1.dist-info/WHEEL
f4-1.1.1.dist-info/top_level.txt
f4-1.1.1.dist-info/RECORD
