Metadata-Version: 2.1
Name: f4
Version: 1.1.1
Summary: A Python package for the Fast Fixed-width File Format (F4)
Home-page: https://github.com/srp33/f4py
Author: Stephen R. Piccolo
Author-email: stephen.piccolo.byu@gmail.com
Project-URL: Docs, https://f4py.readthedocs.io
Classifier: Programming Language :: Python :: 3
Classifier: License :: OSI Approved :: Apache Software License
Classifier: Operating System :: OS Independent
Requires-Python: >=3.6
License-File: LICENSE
Requires-Dist: fastnumbers ==4.0.1
Requires-Dist: joblib ==1.2.0
Requires-Dist: msgspec ==0.13.1
Requires-Dist: zstandard ==0.19.0
